ascii_art.py
config.py
pyfetch.py
system_info.py
devid_pyfetch-0.1.0.dist-info/METADATA
devid_pyfetch-0.1.0.dist-info/WHEEL
devid_pyfetch-0.1.0.dist-info/entry_points.txt
devid_pyfetch-0.1.0.dist-info/top_level.txt
devid_pyfetch-0.1.0.dist-info/RECORD
