Metadata-Version: 2.1
Name: devid-pyfetch
Version: 0.1.0
Summary: Un fork di Neofetch scritto in Python che mostra informazioni di sistema con ASCII art
Home-page: https://github.com/dddevid/pyfetch
Author: PyFetch Team
Author-email: devidrru@gmail.com
Classifier: Programming Language :: Python :: 3
Classifier: Programming Language :: Python :: 3.6
Classifier: Programming Language :: Python :: 3.7
Classifier: Programming Language :: Python :: 3.8
Classifier: Programming Language :: Python :: 3.9
Classifier: Programming Language :: Python :: 3.10
Classifier: Programming Language :: Python :: 3.11
Classifier: Programming Language :: Python :: 3.12
Classifier: Programming Language :: Python :: 3.13
Classifier: License :: OSI Approved :: MIT License
Classifier: Operating System :: OS Independent
Classifier: Environment :: Console
Classifier: Topic :: System :: Monitoring
Requires-Python: >=3.6
Requires-Dist: psutil>=5.9.0
Requires-Dist: wmi>=1.5.1
